semanticpingback.py
SemanticPingback-0.1.1.dist-info/LICENSE
SemanticPingback-0.1.1.dist-info/METADATA
SemanticPingback-0.1.1.dist-info/WHEEL
SemanticPingback-0.1.1.dist-info/top_level.txt
SemanticPingback-0.1.1.dist-info/RECORD
