Metadata-Version: 2.1
Name: SemanticPingback
Version: 0.1.1
Summary: SemanticPingback Server Library for Python
Home-page: https://github.com/AKSW/SemanticPingbackPy
Author: Natanael Arndt
Author-email: arndtn@gmail.com
License: MIT
Platform: any
Classifier: Environment :: Web Environment
Classifier: Intended Audience :: Developers
Classifier: License :: OSI Approved :: MIT License
Classifier: Operating System :: OS Independent
Classifier: Programming Language :: Python
Classifier: Topic :: Internet :: WWW/HTTP :: Dynamic Content
Classifier: Topic :: Software Development :: Libraries :: Python Modules
Requires-Dist: rdflib
